{
  "$schema": "https://demotime.show/demo-time.schema.json",
  "title": "1 - Intro",
  "description": "",
  "version": 2,
  "demos": [
    {
      "title": "Intro",
      "description": "",
      "steps": [
        {
          "action": "executeVSCodeCommand",
          "command": "workbench.action.terminal.killAll"
        },
        {
          "action": "executeVSCodeCommand",
          "command": "workbench.action.closeSidebar"
        },
        {
          "action": "openSlide",
          "path": "/.demo/slides/01-intro/title.md"
        }
      ],
      "icons": {
        "start": "vm",
        "end": "pass-filled"
      }
    },
    {
      "title": "Why async messaging?",
      "description": "",
      "steps": [
        {
          "action": "openSlide",
          "path": "/.demo/slides/01-intro/why.md"
        }
      ],
      "icons": {
        "start": "vm",
        "end": "pass-filled"
      }
    },
    {
      "id": "demo-mf4id3ib-w1uk",
      "title": "Show QR",
      "steps": [
        {
          "action": "startEngageTimeSession",
          "sessionId": "{SESSION_ID}"
        },
        {
          "action": "showEngageTimeSession",
          "sessionId": "{SESSION_ID}"
        }
      ]
    },
    {
      "id": "demo-mf4il91k-xct9",
      "title": "How familiar are you with Dapr?",
      "steps": [
        {
          "action": "startEngageTimePoll",
          "sessionId": "{SESSION_ID}",
          "pollId": "spxbf2"
        },
        {
          "action": "showEngageTimePoll",
          "sessionId": "{SESSION_ID}",
          "pollId": "spxbf2"
        }
      ],
      "icons": {
        "start": "question",
        "end": ""
      }
    },
    {
      "id": "demo-mf4iv9ph-ec6c",
      "title": "Who owns Dapr?",
      "steps": [
        {
          "action": "startEngageTimePoll",
          "sessionId": "{SESSION_ID}",
          "pollId": "zidssc"
        },
        {
          "action": "showEngageTimePoll",
          "sessionId": "{SESSION_ID}",
          "pollId": "zidssc"
        }
      ],
      "icons": {
        "start": "question",
        "end": ""
      }
    },
    {
      "title": "Bio",
      "description": "",
      "steps": [
        {
          "action": "openSlide",
          "path": "/.demo/slides/01-intro/bio.md"
        }
      ],
      "icons": {
        "start": "vm",
        "end": "pass-filled"
      }
    }
  ]
}